yolov7tools/__init__.py
yolov7tools/constants.py
yolov7tools/detection.py
yolov7tools/bin/__init__.py
yolov7tools/bin/launch_cvat.py
yolov7tools/bin/launch_fiftyone.py
yolov7tools/convert/__init__.py
yolov7tools/convert/cvat.py
yolov7tools/convert/fiftyone.py
yolov7tools/convert/idtrackerai.py
yolov7tools/convert/yolov7.py
yolov7tools/export/__init__.py
yolov7tools/export/export.py
yolov7tools/utils/__init__.py
yolov7tools/utils/detections.py
yolov7tools-1.1.dist-info/METADATA
yolov7tools-1.1.dist-info/WHEEL
yolov7tools-1.1.dist-info/entry_points.txt
yolov7tools-1.1.dist-info/top_level.txt
yolov7tools-1.1.dist-info/RECORD
